camoufox_scraper-0.13.0.dist-info/METADATA
camoufox_scraper-0.13.0.dist-info/WHEEL
camoufox_scraper-0.13.0.dist-info/entry_points.txt
camoufox_scraper-0.13.0.dist-info/licenses/LICENSE.txt
camoufox_scraper/__init__.py
camoufox_scraper/lib/__init__.py
camoufox_scraper/lib/base.py
camoufox_scraper/lib/factory.py
camoufox_scraper/lib/scrapers/__init__.py
camoufox_scraper/lib/scrapers/freevideos.py
camoufox_scraper/lib/scrapers/hqporner.py
camoufox_scraper/lib/utils/__init__.py
camoufox_scraper/lib/utils/camoufox_handler.py
camoufox_scraper/scraper.py
camoufox_scraper-0.13.0.dist-info/RECORD
