Metadata-Version: 2.1
Name: camoufox-scraper
Version: 0.13.0
Summary: Add your description here
Author-Email: Tadeas Fort <business@tadeasfort.com>
License: GPL-3.0
Requires-Python: >=3.12
Requires-Dist: camoufox[geoip]>=0.4.11
Requires-Dist: yt-dlp>=2025.2.19
Requires-Dist: prompt-toolkit>=3.0.33
Requires-Dist: requests>=2.28.2
Requires-Dist: typer>=0.15.2
Requires-Dist: playwright>=1.38.0
Requires-Dist: aiohttp>=3.8.4
